{
  "intents": [
    {
      "intent": "GenericIntent",
      "slots": [
          {
              "name": "MeasurementType",
              "type": "LIST_OF_MEASUREMENT_TYPES"
          },
          {
              "name": "TimeFrame",
              "type": "LIST_OF_TIME_FRAME"
          },
          {
              "name": "PreTime",
              "type": "LIST_OF_PRE_TIME"
          },
          {
              "name": "Multiple",
              "type": "AMAZON.NUMBER"
          }
      ]
    },
    {
      "intent": "HighLowAvgIntent",
      "slots": [
          {
              "name": "MeasurementType",
              "type": "LIST_OF_MEASUREMENT_TYPES"
          },
          {
              "name": "HighLowAvg",
              "type": "LIST_OF_HIGH_LOW_AVG"
          },
          {
              "name": "TimeFrame",
              "type": "LIST_OF_TIME_FRAME"
          },
          {
              "name": "PreTime",
              "type": "LIST_OF_PRE_TIME"
          },
          {
              "name": "Multiple",
              "type": "AMAZON.NUMBER"
          }
      ]
    },
    {
      "intent": "TrendIntent",
      "slots": [
          {
              "name": "MeasurementType",
              "type": "LIST_OF_MEASUREMENT_TYPES"
          },
          {
              "name": "TrendType",
              "type": "LIST_OF_TREND_TYPES"
          },
          {
              "name": "TimeFrame",
              "type": "LIST_OF_TIME_FRAME"
          },
          {
              "name": "PreTime",
              "type": "LIST_OF_PRE_TIME"
          },
          {
              "name": "Multiple",
              "type": "AMAZON.NUMBER"
          }
      ]
    },
    {
      "intent": "HelpIntent",
      "slots": []
    }
  ]
}
